autofile/__init__.py
autofile/auto_detect.py
autofile/wrappers.py
tests/__init__.py
tests/test_detect.py
tests/test_read.py
textfile_autoencoding-2020.3.17.dist-info/LICENSE
textfile_autoencoding-2020.3.17.dist-info/METADATA
textfile_autoencoding-2020.3.17.dist-info/WHEEL
textfile_autoencoding-2020.3.17.dist-info/top_level.txt
textfile_autoencoding-2020.3.17.dist-info/RECORD
